LICENSE
MANIFEST.in
README.rst
setup.cfg
setup.py
fingo_django_graphiql_debug_toolbar.egg-info/PKG-INFO
fingo_django_graphiql_debug_toolbar.egg-info/SOURCES.txt
fingo_django_graphiql_debug_toolbar.egg-info/dependency_links.txt
fingo_django_graphiql_debug_toolbar.egg-info/not-zip-safe
fingo_django_graphiql_debug_toolbar.egg-info/requires.txt
fingo_django_graphiql_debug_toolbar.egg-info/top_level.txt
graphiql_debug_toolbar/__init__.py
graphiql_debug_toolbar/middleware.py
graphiql_debug_toolbar/serializers.py
graphiql_debug_toolbar/static/graphiql_debug_toolbar/js/parse.js
graphiql_debug_toolbar/templates/graphiql_debug_toolbar/base.html