Metadata-Version: 1.2
Name: fingo-django-graphiql-debug-toolbar
Version: 0.1.4
Summary: Django Debug Toolbar for GraphiQL IDE
Home-page: https://github.com/diegobordeu/django-graphiql-debug-toolbar/
Author: mongkok
Author-email: domake.io@gmail.com
Maintainer: mongkok
License: MIT
Platform: UNKNOWN
Classifier: Development Status :: 1 - Planning
Classifier: Environment :: Web Environment
Classifier: Intended Audience :: Developers
Classifier: License :: OSI Approved :: MIT License
Classifier: Operating System :: OS Independent
Classifier: Programming Language :: Python
Classifier: Programming Language :: Python :: 3
Classifier: Programming Language :: Python :: 3.5
Classifier: Programming Language :: Python :: 3.6
Classifier: Programming Language :: Python :: 3.7
Classifier: Programming Language :: Python :: 3.8
Classifier: Framework :: Django
Classifier: Framework :: Django :: 2.0
Classifier: Framework :: Django :: 2.1
Classifier: Framework :: Django :: 2.2
